Metadata-Version: 1.1
Name: ngs-plumbing
Version: 0.13.1
Summary: Plumbing for NGS data
Home-page: UNKNOWN
Author: Laurent Gautier
Author-email: lgautier@gmail.com
License: UNKNOWN
Platform: UNKNOWN
Classifier: Programming Language :: Python :: 2
Classifier: Programming Language :: Python :: 3
Classifier: License :: OSI Approved :: GNU Affero General Public License v3
Classifier: License :: Free for non-commercial use
Classifier: Intended Audience :: Developers
Classifier: Intended Audience :: Science/Research
Classifier: Development Status :: 4 - Beta
